makebio/__init__.py
makebio/about.py
makebio/cli.py
makebio/config/gitignore
makebio-0.34.dist-info/entry_points.txt
makebio-0.34.dist-info/LICENSE
makebio-0.34.dist-info/WHEEL
makebio-0.34.dist-info/METADATA
makebio-0.34.dist-info/RECORD
