Metadata-Version: 2.1
Name: makebio
Version: 0.34
Summary: Manage your computational biology research projects
Author: Vivek Rai
Author-email: vivekrai@umich.edu
Requires-Python: >=3.7,<4.0
Classifier: Programming Language :: Python :: 3
Classifier: Programming Language :: Python :: 3.7
Classifier: Programming Language :: Python :: 3.8
Classifier: Programming Language :: Python :: 3.9
Requires-Dist: click (>=7.0,<8.0)
Requires-Dist: colorama (>=0.4.3,<0.5.0)
Requires-Dist: toml (>=0.10.0,<0.11.0)
